lvg_norm/__init__.py
lvg_norm/__main__.py
lvg_norm/cli.py
lvg_norm/lexicon.py
lvg_norm/norm.py
lvg_norm/resources/Unicode/__init__.py
lvg_norm/resources/Unicode/diacriticMap.data
lvg_norm/resources/Unicode/ligatureMap.data
lvg_norm/resources/Unicode/nonStripMap.data
lvg_norm/resources/Unicode/symbolMap.data
lvg_norm/resources/Unicode/synonymMap.data
lvg_norm/resources/Unicode/unicodeMap.data
lvg_norm/resources/__init__.py
lvg_norm/resources/misc/__init__.py
lvg_norm/resources/misc/removeS.data
lvg_norm/resources/misc/stopWords.data
lvg_norm/resources/rules/__init__.py
lvg_norm/resources/rules/im.rul
lvg_norm/resources/rules/plural.rul
lvg_norm/resources/rules/verbinfl.rul
lvg_norm/resources/tables/__init__.py
lvg_norm/resources/tables/infl.data.gz
lvg_norm/unicode_data.py
lvg_norm/wordlists.py
lvg_norm-1.1.0.dist-info/WHEEL
lvg_norm-1.1.0.dist-info/entry_points.txt
lvg_norm-1.1.0.dist-info/METADATA
lvg_norm-1.1.0.dist-info/RECORD
