Metadata-Version: 2.3
Name: lvg_norm
Version: 1.1.0
Summary: Python implementation of LVG Norm (https://lhncbc.nlm.nih.gov/LSG/Projects/lvg/current/docs/userDoc/tools/norm.html)
Author: Haydn Jones
Author-email: Haydn Jones <haydnjonest@gmail.com>
Requires-Dist: pytest>=8.3 ; extra == 'dev'
Requires-Dist: ruff>=0.6.9 ; extra == 'dev'
Requires-Python: >=3.12
Provides-Extra: dev
